actionqueues/__init__.py
actionqueues/action.py
actionqueues/actionqueue.py
actionqueues/aqstatemachine.py
actionqueues/exceptionfactory.py
actionqueues-0.8.2.dist-info/METADATA
actionqueues-0.8.2.dist-info/RECORD
actionqueues-0.8.2.dist-info/WHEEL
actionqueues-0.8.2.dist-info/top_level.txt
