Metadata-Version: 2.1
Name: actionqueues
Version: 0.8.2
Summary: Framework for executing actions and rollbacks
Home-page: http://github.com/mikerhodes/actionqueues
Author: Mike Rhodes
Author-email: mike.rhodes@dx13.co.uk
License: Apache 2.0
Platform: UNKNOWN
Classifier: License :: OSI Approved :: Apache Software License
Classifier: Operating System :: OS Independent
